discord_bot_generator/__init__.py
discord_bot_generator/__main__.py
discord_bot_generator/__version__.py
discord_bot_generator/cli.py
discord_bot_generator/config.py
discord_bot_generator/generator.py
discord_bot_generator-0.0.1.dist-info/LICENSE
discord_bot_generator-0.0.1.dist-info/METADATA
discord_bot_generator-0.0.1.dist-info/WHEEL
discord_bot_generator-0.0.1.dist-info/entry_points.txt
discord_bot_generator-0.0.1.dist-info/top_level.txt
discord_bot_generator-0.0.1.dist-info/RECORD
