Metadata-Version: 2.1
Name: discord-bot-generator
Version: 0.0.1
Summary: Fastest and easiest way to create a new discord bot project ✨🚀
Home-page: https://github.com/SyedAhkam/discord-bot-generator
Author: SyedAhkam
Author-email: smahkam57@gmail.com
License: MIT
Platform: UNKNOWN
Classifier: Programming Language :: Python :: 3
Classifier: License :: OSI Approved :: MIT License
Classifier: Operating System :: OS Independent
Requires-Python: >=3.6
Requires-Dist: click
Requires-Dist: colorama
